agent_framework_declarative/__init__.py
agent_framework_declarative/_loader.py
agent_framework_declarative/_models.py
agent_framework_declarative/_workflows/__init__.py
agent_framework_declarative/_workflows/_actions_agents.py
agent_framework_declarative/_workflows/_actions_basic.py
agent_framework_declarative/_workflows/_actions_control_flow.py
agent_framework_declarative/_workflows/_actions_error.py
agent_framework_declarative/_workflows/_declarative_base.py
agent_framework_declarative/_workflows/_declarative_builder.py
agent_framework_declarative/_workflows/_executors_agents.py
agent_framework_declarative/_workflows/_executors_basic.py
agent_framework_declarative/_workflows/_executors_control_flow.py
agent_framework_declarative/_workflows/_executors_external_input.py
agent_framework_declarative/_workflows/_factory.py
agent_framework_declarative/_workflows/_handlers.py
agent_framework_declarative/_workflows/_human_input.py
agent_framework_declarative/_workflows/_powerfx_functions.py
agent_framework_declarative/_workflows/_state.py
agent_framework_declarative-1.0.0b260114.dist-info/licenses/LICENSE
agent_framework_declarative-1.0.0b260114.dist-info/WHEEL
agent_framework_declarative-1.0.0b260114.dist-info/METADATA
agent_framework_declarative-1.0.0b260114.dist-info/RECORD
